nbmeta/__init__.py
nbmeta/_core.py
nbmeta-0.1a1.dist-info/LICENSE
nbmeta-0.1a1.dist-info/WHEEL
nbmeta-0.1a1.dist-info/METADATA
nbmeta-0.1a1.dist-info/RECORD
