Metadata-Version: 2.1
Name: nbmeta
Version: 0.1a1
Summary: Manage Jupyter notebooks.
Author-email: Lamin Labs <laminlabs@gmail.com>
Requires-Dist: nbproject
Requires-Dist: pre-commit ; extra == "dev"
Requires-Dist: nox ; extra == "dev"
Requires-Dist: pytest>=6.0 ; extra == "test"
Requires-Dist: nbmake ; extra == "test"
Project-URL: Home, https://github.com/laminlabs/nbmeta
Provides-Extra: dev
Provides-Extra: test
